<annotation>
	<folder>verified</folder>
	<filename>05c24cf76451effd15a040dbd56cb95c-20.png</filename>
	<path>\\192.168.150.246\applications\dataset_tables_2021\verified\05c24cf76451effd15a040dbd56cb95c-20.jpg</path>
	<source>
		<database>Unknown</database>
	</source>
	<size>
		<width>1224</width>
		<height>1584</height>
		<depth>1</depth>
	</size>
	<segmented>0</segmented>
	<object>
		<name>partial_lined_merged_cells</name>
		<pose>Unspecified</pose>
		<truncated>0</truncated>
		<difficult>0</difficult>
		<bndbox>
			<xmin>166</xmin>
			<ymin>934</ymin>
			<xmax>1010</xmax>
			<ymax>1218</ymax>
		</bndbox>
	</object>
</annotation>