<annotation>
	<folder>data_nolines</folder>
	<filename>13cbad2a7c6cf1580dc6c335cf39eda6-61.png</filename>
	<path>\\192.168.150.246\applications\data_nolines\13cbad2a7c6cf1580dc6c335cf39eda6-61.jpg</path>
	<source>
		<database>Unknown</database>
	</source>
	<size>
		<width>1254</width>
		<height>1610</height>
		<depth>1</depth>
	</size>
	<segmented>0</segmented>
	<object>
		<name>nolines</name>
		<pose>Unspecified</pose>
		<truncated>0</truncated>
		<difficult>0</difficult>
		<bndbox>
			<xmin>132</xmin>
			<ymin>261</ymin>
			<xmax>977</xmax>
			<ymax>700</ymax>
		</bndbox>
	</object>
</annotation>