<annotation>
	<folder>full_lined_300more</folder>
	<filename>1a97307c26b1f5a70a4343c80d973663.jpg</filename>
	<path>\\192.168.150.246\applications\dataset_tables_need_verify\full_lined_300more\1a97307c26b1f5a70a4343c80d973663.jpg</path>
	<source>
		<database>Unknown</database>
	</source>
	<size>
		<width>1685</width>
		<height>1191</height>
		<depth>3</depth>
	</size>
	<segmented>0</segmented>
	<object>
		<name>full_lined</name>
		<pose>Unspecified</pose>
		<truncated>0</truncated>
		<difficult>0</difficult>
		<bndbox>
			<xmin>210</xmin>
			<ymin>140</ymin>
			<xmax>1441</xmax>
			<ymax>1033</ymax>
		</bndbox>
	</object>
</annotation>