<annotation>
	<folder>merged_cells_1</folder>
	<filename>2a0e665f09475308f80a89a4dc3625e6.jpg</filename>
	<path>\\192.168.150.246\applications\dataset_tables_need_verify\merged_cells_1\2a0e665f09475308f80a89a4dc3625e6.jpg</path>
	<source>
		<database>Unknown</database>
	</source>
	<size>
		<width>1586</width>
		<height>1224</height>
		<depth>1</depth>
	</size>
	<segmented>0</segmented>
	<object>
		<name>full_lined</name>
		<pose>Unspecified</pose>
		<truncated>0</truncated>
		<difficult>0</difficult>
		<bndbox>
			<xmin>171</xmin>
			<ymin>849</ymin>
			<xmax>1420</xmax>
			<ymax>887</ymax>
		</bndbox>
	</object>
	<object>
		<name>full_lined</name>
		<pose>Unspecified</pose>
		<truncated>0</truncated>
		<difficult>0</difficult>
		<bndbox>
			<xmin>175</xmin>
			<ymin>985</ymin>
			<xmax>1420</xmax>
			<ymax>1042</ymax>
		</bndbox>
	</object>
	<object>
		<name>merged_cells</name>
		<pose>Unspecified</pose>
		<truncated>0</truncated>
		<difficult>0</difficult>
		<bndbox>
			<xmin>172</xmin>
			<ymin>426</ymin>
			<xmax>1421</xmax>
			<ymax>722</ymax>
		</bndbox>
	</object>
	<object>
		<name>merged_cells</name>
		<pose>Unspecified</pose>
		<truncated>0</truncated>
		<difficult>0</difficult>
		<bndbox>
			<xmin>171</xmin>
			<ymin>279</ymin>
			<xmax>1424</xmax>
			<ymax>372</ymax>
		</bndbox>
	</object>
	<object>
		<name>full_lined</name>
		<pose>Unspecified</pose>
		<truncated>0</truncated>
		<difficult>0</difficult>
		<bndbox>
			<xmin>173</xmin>
			<ymin>384</ymin>
			<xmax>1423</xmax>
			<ymax>405</ymax>
		</bndbox>
	</object>
</annotation>