<annotation>
	<folder>verified</folder>
	<filename>2ec18c0a359f59361c175285789c128f.jpg</filename>
	<path>\\192.168.150.246\applications\dataset_tables_2021\verified\2ec18c0a359f59361c175285789c128f.jpg</path>
	<source>
		<database>Unknown</database>
	</source>
	<size>
		<width>1191</width>
		<height>1684</height>
		<depth>3</depth>
	</size>
	<segmented>0</segmented>
	<object>
		<name>partial_lined</name>
		<pose>Unspecified</pose>
		<truncated>0</truncated>
		<difficult>0</difficult>
		<bndbox>
			<xmin>152</xmin>
			<ymin>459</ymin>
			<xmax>1081</xmax>
			<ymax>740</ymax>
		</bndbox>
	</object>
	<object>
		<name>partial_lined</name>
		<pose>Unspecified</pose>
		<truncated>0</truncated>
		<difficult>0</difficult>
		<bndbox>
			<xmin>151</xmin>
			<ymin>988</ymin>
			<xmax>1083</xmax>
			<ymax>1396</ymax>
		</bndbox>
	</object>
</annotation>