<annotation>
	<folder>full_lined_300more3</folder>
	<filename>44d451289f43eff188d44d2d95c139e2.jpg</filename>
	<path>\\192.168.150.246\applications\dataset_tables_need_verify\full_lined_300more3\44d451289f43eff188d44d2d95c139e2.jpg</path>
	<source>
		<database>Unknown</database>
	</source>
	<size>
		<width>1684</width>
		<height>1191</height>
		<depth>3</depth>
	</size>
	<segmented>0</segmented>
	<object>
		<name>full_lined</name>
		<pose>Unspecified</pose>
		<truncated>0</truncated>
		<difficult>0</difficult>
		<bndbox>
			<xmin>138</xmin>
			<ymin>124</ymin>
			<xmax>1540</xmax>
			<ymax>1037</ymax>
		</bndbox>
	</object>
</annotation>