<annotation>
	<folder>merged_cells_1</folder>
	<filename>47754e1d38d55d1f3a4b46a42cf5bc6b.jpg</filename>
	<path>\\192.168.150.246\applications\dataset_tables_need_verify\merged_cells_1\47754e1d38d55d1f3a4b46a42cf5bc6b.jpg</path>
	<source>
		<database>Unknown</database>
	</source>
	<size>
		<width>1192</width>
		<height>1685</height>
		<depth>3</depth>
	</size>
	<segmented>0</segmented>
	<object>
		<name>merged_cells</name>
		<pose>Unspecified</pose>
		<truncated>0</truncated>
		<difficult>0</difficult>
		<bndbox>
			<xmin>112</xmin>
			<ymin>69</ymin>
			<xmax>1103</xmax>
			<ymax>255</ymax>
		</bndbox>
	</object>
</annotation>