<annotation>
	<folder>merged_cells_2_300_0</folder>
	<filename>838fdb41e256e61b0a960d349e77fb23.jpg</filename>
	<path>\\192.168.150.246\applications\dataset_tables_need_verify\merged_cells_2_300_0\838fdb41e256e61b0a960d349e77fb23.jpg</path>
	<source>
		<database>Unknown</database>
	</source>
	<size>
		<width>1191</width>
		<height>1684</height>
		<depth>1</depth>
	</size>
	<segmented>0</segmented>
	<object>
		<name>merged_cells</name>
		<pose>Unspecified</pose>
		<truncated>0</truncated>
		<difficult>0</difficult>
		<bndbox>
			<xmin>168</xmin>
			<ymin>432</ymin>
			<xmax>1009</xmax>
			<ymax>1342</ymax>
		</bndbox>
	</object>
</annotation>