<annotation>
	<folder>merged_cells_2_300_0</folder>
	<filename>88c4926a28a8e7993f8b87c81934f963.jpg</filename>
	<path>\\192.168.150.246\applications\dataset_tables_need_verify\merged_cells_2_300_0\88c4926a28a8e7993f8b87c81934f963.jpg</path>
	<source>
		<database>Unknown</database>
	</source>
	<size>
		<width>1224</width>
		<height>1585</height>
		<depth>3</depth>
	</size>
	<segmented>0</segmented>
	<object>
		<name>full_lined</name>
		<pose>Unspecified</pose>
		<truncated>0</truncated>
		<difficult>0</difficult>
		<bndbox>
			<xmin>293</xmin>
			<ymin>939</ymin>
			<xmax>982</xmax>
			<ymax>1116</ymax>
		</bndbox>
	</object>
	<object>
		<name>merged_cells</name>
		<pose>Unspecified</pose>
		<truncated>0</truncated>
		<difficult>0</difficult>
		<bndbox>
			<xmin>287</xmin>
			<ymin>280</ymin>
			<xmax>981</xmax>
			<ymax>888</ymax>
		</bndbox>
	</object>
</annotation>