<annotation>
    <folder />
    <filename>98a6f814bb290dccfc941f08a77d96f4.jpg</filename>
    <path>98a6f814bb290dccfc941f08a77d96f4.jpg</path>
    <source>
        <database>Unknown</database>
    </source>
    <size>
        <width>0</width>
        <height>0</height>
        <depth>3</depth>
    </size>
    <segmented />
    <object>
        <name>full_lined</name>
        <pose>Unspecified</pose>
        <truncated>0</truncated>
        <difficult>0</difficult>
        <bndbox>
            <xmin>233</xmin>
            <ymin>140</ymin>
            <xmax>968</xmax>
            <ymax>1506</ymax>
        </bndbox>
    </object>
</annotation>