<annotation>
	<folder>partial_lined_2_verifying</folder>
	<filename>98d2b3657734e812b94d8dfdcf506fa9.jpg</filename>
	<path>\\192.168.150.246\applications\dataset_tables_need_verify\partial_lined_2_verifying\98d2b3657734e812b94d8dfdcf506fa9.jpg</path>
	<source>
		<database>Unknown</database>
	</source>
	<size>
		<width>1193</width>
		<height>1684</height>
		<depth>3</depth>
	</size>
	<segmented>0</segmented>
	<object>
		<name>nolines</name>
		<pose>Unspecified</pose>
		<truncated>0</truncated>
		<difficult>0</difficult>
		<bndbox>
			<xmin>77</xmin>
			<ymin>289</ymin>
			<xmax>979</xmax>
			<ymax>488</ymax>
		</bndbox>
	</object>
	<object>
		<name>nolines</name>
		<pose>Unspecified</pose>
		<truncated>0</truncated>
		<difficult>0</difficult>
		<bndbox>
			<xmin>45</xmin>
			<ymin>968</ymin>
			<xmax>1066</xmax>
			<ymax>1533</ymax>
		</bndbox>
	</object>
	<object>
		<name>partial_lined</name>
		<pose>Unspecified</pose>
		<truncated>0</truncated>
		<difficult>0</difficult>
		<bndbox>
			<xmin>50</xmin>
			<ymin>540</ymin>
			<xmax>1066</xmax>
			<ymax>950</ymax>
		</bndbox>
	</object>
</annotation>