<annotation>
	<folder>full_lined_300more3</folder>
	<filename>9b065f7998e4eff6740ee1dd8eff310c.jpg</filename>
	<path>\\192.168.150.246\applications\dataset_tables_need_verify\full_lined_300more3\9b065f7998e4eff6740ee1dd8eff310c.jpg</path>
	<source>
		<database>Unknown</database>
	</source>
	<size>
		<width>1192</width>
		<height>1684</height>
		<depth>3</depth>
	</size>
	<segmented>0</segmented>
	<object>
		<name>full_lined</name>
		<pose>Unspecified</pose>
		<truncated>0</truncated>
		<difficult>0</difficult>
		<bndbox>
			<xmin>147</xmin>
			<ymin>141</ymin>
			<xmax>1062</xmax>
			<ymax>198</ymax>
		</bndbox>
	</object>
	<object>
		<name>full_lined</name>
		<pose>Unspecified</pose>
		<truncated>0</truncated>
		<difficult>0</difficult>
		<bndbox>
			<xmin>147</xmin>
			<ymin>1515</ymin>
			<xmax>1081</xmax>
			<ymax>1571</ymax>
		</bndbox>
	</object>
</annotation>