<annotation>
	<folder>merged_cells_2_300_1</folder>
	<filename>ada8d51e4b58c92e86e74343c1ddb144.jpg</filename>
	<path>\\192.168.150.246\applications\dataset_tables_need_verify\merged_cells_2_300_1\ada8d51e4b58c92e86e74343c1ddb144.jpg</path>
	<source>
		<database>Unknown</database>
	</source>
	<size>
		<width>1685</width>
		<height>2382</height>
		<depth>3</depth>
	</size>
	<segmented>0</segmented>
	<object>
		<name>merged_cells</name>
		<pose>Unspecified</pose>
		<truncated>0</truncated>
		<difficult>0</difficult>
		<bndbox>
			<xmin>344</xmin>
			<ymin>1974</ymin>
			<xmax>858</xmax>
			<ymax>2280</ymax>
		</bndbox>
	</object>
	<object>
		<name>merged_cells</name>
		<pose>Unspecified</pose>
		<truncated>0</truncated>
		<difficult>0</difficult>
		<bndbox>
			<xmin>1314</xmin>
			<ymin>1787</ymin>
			<xmax>1655</xmax>
			<ymax>1969</ymax>
		</bndbox>
	</object>
	<object>
		<name>merged_cells</name>
		<pose>Unspecified</pose>
		<truncated>0</truncated>
		<difficult>0</difficult>
		<bndbox>
			<xmin>344</xmin>
			<ymin>70</ymin>
			<xmax>972</xmax>
			<ymax>278</ymax>
		</bndbox>
	</object>
</annotation>