<annotation>
	<folder>merged_cells_2_300_1</folder>
	<filename>b4e96336ac8db11d3ce079d9724eb731.jpg</filename>
	<path>\\192.168.150.246\applications\dataset_tables_need_verify\merged_cells_2_300_1\b4e96336ac8db11d3ce079d9724eb731.jpg</path>
	<source>
		<database>Unknown</database>
	</source>
	<size>
		<width>908</width>
		<height>1361</height>
		<depth>3</depth>
	</size>
	<segmented>0</segmented>
	<object>
		<name>merged_cells</name>
		<pose>Unspecified</pose>
		<truncated>0</truncated>
		<difficult>0</difficult>
		<bndbox>
			<xmin>140</xmin>
			<ymin>328</ymin>
			<xmax>795</xmax>
			<ymax>703</ymax>
		</bndbox>
	</object>
</annotation>