<annotation>
	<folder>merged_cells_2_300_1</folder>
	<filename>b50f1cf7b044097fb7930760d9fe0180.jpg</filename>
	<path>\\192.168.150.246\applications\dataset_tables_need_verify\merged_cells_2_300_1\b50f1cf7b044097fb7930760d9fe0180.jpg</path>
	<source>
		<database>Unknown</database>
	</source>
	<size>
		<width>1191</width>
		<height>1684</height>
		<depth>3</depth>
	</size>
	<segmented>0</segmented>
	<object>
		<name>merged_cells</name>
		<pose>Unspecified</pose>
		<truncated>0</truncated>
		<difficult>0</difficult>
		<bndbox>
			<xmin>101</xmin>
			<ymin>148</ymin>
			<xmax>1110</xmax>
			<ymax>332</ymax>
		</bndbox>
	</object>
</annotation>