<annotation>
	<folder>data</folder>
	<filename>d2c1818e3e088adf9e21874a31766c3f.jpg</filename>
	<path>C:\Users\i.nuradin\Desktop\data\d2c1818e3e088adf9e21874a31766c3f.jpg</path>
	<source>
		<database>Unknown</database>
	</source>
	<size>
		<width>1192</width>
		<height>1685</height>
		<depth>3</depth>
	</size>
	<segmented>0</segmented>
	<object>
		<name>full_lined</name>
		<pose>Unspecified</pose>
		<truncated>0</truncated>
		<difficult>0</difficult>
		<bndbox>
			<xmin>137</xmin>
			<ymin>253</ymin>
			<xmax>1053</xmax>
			<ymax>1399</ymax>
		</bndbox>
	</object>
	<object>
		<name>merged_cells</name>
		<pose>Unspecified</pose>
		<truncated>0</truncated>
		<difficult>0</difficult>
		<bndbox>
			<xmin>112</xmin>
			<ymin>70</ymin>
			<xmax>1104</xmax>
			<ymax>227</ymax>
		</bndbox>
	</object>
</annotation>