<annotation>
	<folder>verified</folder>
	<filename>e1e6ab7d264ca53a015c5d65836f7cbb.jpg</filename>
	<path>\\192.168.150.246\applications\dataset_tables_2021\verified\e1e6ab7d264ca53a015c5d65836f7cbb.jpg</path>
	<source>
		<database>Unknown</database>
	</source>
	<size>
		<width>1191</width>
		<height>1681</height>
		<depth>3</depth>
	</size>
	<segmented>0</segmented>
	<object>
		<name>full_lined</name>
		<pose>Unspecified</pose>
		<truncated>0</truncated>
		<difficult>0</difficult>
		<bndbox>
			<xmin>168</xmin>
			<ymin>1159</ymin>
			<xmax>862</xmax>
			<ymax>1211</ymax>
		</bndbox>
	</object>
	<object>
		<name>nolines</name>
		<pose>Unspecified</pose>
		<truncated>0</truncated>
		<difficult>0</difficult>
		<bndbox>
			<xmin>157</xmin>
			<ymin>262</ymin>
			<xmax>775</xmax>
			<ymax>490</ymax>
		</bndbox>
	</object>
</annotation>