<annotation>
	<folder>verified</folder>
	<filename>ef7efb03f54138be73a35f9eb7433b0c.jpg</filename>
	<path>\\192.168.150.246\applications\dataset_tables_2021\verified\ef7efb03f54138be73a35f9eb7433b0c.jpg</path>
	<source>
		<database>Unknown</database>
	</source>
	<size>
		<width>1191</width>
		<height>1684</height>
		<depth>3</depth>
	</size>
	<segmented>0</segmented>
	<object>
		<name>partial_lined</name>
		<pose>Unspecified</pose>
		<truncated>0</truncated>
		<difficult>0</difficult>
		<bndbox>
			<xmin>157</xmin>
			<ymin>382</ymin>
			<xmax>1079</xmax>
			<ymax>599</ymax>
		</bndbox>
	</object>
	<object>
		<name>partial_lined</name>
		<pose>Unspecified</pose>
		<truncated>0</truncated>
		<difficult>0</difficult>
		<bndbox>
			<xmin>157</xmin>
			<ymin>987</ymin>
			<xmax>1078</xmax>
			<ymax>1108</ymax>
		</bndbox>
	</object>
</annotation>